{
  "$schema": "lia-fingerprint-v1",
  "id": "recog-microsoft_azure_app_service_on_azure_stack",
  "version": "1.0.0",
  "enabled": true,
  "taxonomy_code": "MICROSOFT_AZURE_APP_SERVICE_ON_AZURE_STACK",
  "taxonomy_name": "Microsoft Azure App Service on Azure Stack",
  "vendor": "Microsoft",
  "product": "Azure App Service on Azure Stack",
  "source": {
    "type": "recog",
    "file": "MICROSOFT_AZURE_APP_SERVICE_ON_AZURE_STACK.json",
    "fingerprint_count": 1
  },
  "research": [
    {
      "url": "https://github.com/rapid7/recog",
      "type": "recog_database",
      "evidence": "Converted from 1 Recog XML fingerprints",
      "date": "2026-02-28"
    }
  ],
  "default_ports": [
    80,
    443,
    8080,
    8443
  ],
  "probes": [
    {
      "id": "recog_microsoft_azure_app_service_on_azure_stack_l7_http",
      "layer": "L7_HTTP",
      "matchers": [
        {
          "target": "body",
          "match_type": "regex",
          "value": "^Microsoft Azure Web App - Error 404$",
          "confidence_delta": 0.4,
          "case_insensitive": true,
          "note": "Microsoft Azure Web App - Error 404"
        }
      ],
      "method": "GET",
      "path": "/",
      "follow_redirects": true
    }
  ],
  "base_confidence": 0.0,
  "confidence_threshold": 0.6,
  "tags": [
    "http"
  ],
  "cpe23_template": "cpe:/a:microsoft:azure_app_service_on_azure_stack:-",
  "examples": [
    "Microsoft Azure Web App - Error 404"
  ]
}