{
  "$schema": "lia-fingerprint-v1",
  "id": "recog-steinsvik_linux",
  "version": "1.0.0",
  "enabled": true,
  "taxonomy_code": "STEINSVIK_LINUX",
  "taxonomy_name": "Steinsvik Linux",
  "vendor": "Steinsvik",
  "product": "Linux",
  "source": {
    "type": "recog",
    "file": "STEINSVIK_LINUX.json",
    "fingerprint_count": 1
  },
  "research": [
    {
      "url": "https://github.com/rapid7/recog",
      "type": "recog_database",
      "evidence": "Converted from 1 Recog XML fingerprints",
      "date": "2026-02-28"
    }
  ],
  "default_ports": [
    80,
    443
  ],
  "probes": [
    {
      "id": "recog_steinsvik_linux_l4_tcp",
      "layer": "L4_TCP",
      "matchers": [
        {
          "target": "banner",
          "match_type": "regex",
          "value": "^Digest realm=\"(Orbit-351)\"",
          "confidence_delta": 0.4,
          "case_insensitive": true,
          "note": "Steinsvik Orbit 351 IP Camera (Truen TCAM Rebrand)"
        }
      ]
    }
  ],
  "base_confidence": 0.0,
  "confidence_threshold": 0.6,
  "tags": [
    "generic"
  ],
  "examples": [
    "Digest realm=\"Orbit-351\", nonce=\"0000040dY892418598785d2a2304a74adf22f6098f2792\", stale=FALSE"
  ]
}