{
  "$schema": "lia-fingerprint-v1",
  "id": "recog-wordpress_wordpress_multi_user_mu",
  "version": "1.0.0",
  "enabled": true,
  "taxonomy_code": "WORDPRESS_WORDPRESS_MULTI_USER_MU",
  "taxonomy_name": "WordPress WordPress Multi-User (MU)",
  "vendor": "WordPress",
  "product": "WordPress Multi-User (MU)",
  "source": {
    "type": "recog",
    "file": "WORDPRESS_WORDPRESS_MULTI_USER_MU.json",
    "fingerprint_count": 1
  },
  "research": [
    {
      "url": "https://github.com/rapid7/recog",
      "type": "recog_database",
      "evidence": "Converted from 1 Recog XML fingerprints",
      "date": "2026-02-28"
    }
  ],
  "default_ports": [
    80,
    443,
    8080,
    8443
  ],
  "probes": [
    {
      "id": "recog_wordpress_wordpress_multi_user_mu_l7_http",
      "layer": "L7_HTTP",
      "matchers": [
        {
          "target": "favicon_hash",
          "match_type": "regex",
          "value": "^95103d0eabcd541527a86f23b636e794",
          "confidence_delta": 0.4,
          "case_insensitive": true,
          "note": "WordPress Multi-User (MU)"
        }
      ],
      "method": "GET",
      "path": "/",
      "follow_redirects": true
    }
  ],
  "base_confidence": 0.0,
  "confidence_threshold": 0.6,
  "tags": [
    "http"
  ],
  "examples": [
    "95103d0eabcd541527a86f23b636e794"
  ]
}