{
  "$schema": "lia-fingerprint-v1",
  "id": "wappalyzer-correos_ecommerce",
  "version": "1.0.0",
  "enabled": true,
  "taxonomy_code": "CORREOS_ECOMMERCE",
  "taxonomy_name": "Correos Ecommerce",
  "vendor": "",
  "product": "Correos Ecommerce",
  "source": {
    "type": "wappalyzer",
    "file": "CORREOS_ECOMMERCE.json",
    "original_name": "Correos Ecommerce"
  },
  "research": [
    {
      "url": "https://www.correosecommerce.com",
      "type": "wappalyzer_database",
      "evidence": "Converted from wappalyzergo fingerprints_data.json",
      "date": "2026-02-28"
    }
  ],
  "default_ports": [
    80,
    443
  ],
  "probes": [
    {
      "id": "wappalyzer_correos_ecommerce_http",
      "layer": "L7_HTTP",
      "method": "GET",
      "path": "/",
      "follow_redirects": true,
      "matchers": [
        {
          "target": "script_src",
          "match_type": "regex",
          "value": "\\.mycorreosecommerce\\.com/",
          "confidence_delta": 0.5
        }
      ]
    }
  ],
  "base_confidence": 0.0,
  "confidence_threshold": 0.6,
  "tags": [],
  "categories": [
    6
  ],
  "notes": "Correos Ecommerce is an ecommerce platfrom from Spain.",
  "website": "https://www.correosecommerce.com"
}