{
  "$schema": "lia-fingerprint-v1",
  "id": "wappalyzer-highlight_js",
  "version": "1.0.0",
  "enabled": true,
  "taxonomy_code": "HIGHLIGHT_JS",
  "taxonomy_name": "Highlight.js",
  "vendor": "",
  "product": "Highlight.js",
  "source": {
    "type": "wappalyzer",
    "file": "HIGHLIGHT_JS.json",
    "original_name": "Highlight.js"
  },
  "research": [
    {
      "url": "https://highlightjs.org/",
      "type": "wappalyzer_database",
      "evidence": "Converted from wappalyzergo fingerprints_data.json",
      "date": "2026-02-28"
    }
  ],
  "default_ports": [
    80,
    443
  ],
  "probes": [
    {
      "id": "wappalyzer_highlight_js_http",
      "layer": "L7_HTTP",
      "method": "GET",
      "path": "/",
      "follow_redirects": true,
      "matchers": [
        {
          "target": "script_src",
          "match_type": "regex",
          "value": "/(?:([\\d.])+/)?highlight(?:\\.min)?\\.js",
          "confidence_delta": 0.5,
          "version_extract": "/(?:([\\d.])+/)?highlight(?:\\.min)?\\.js"
        }
      ]
    }
  ],
  "base_confidence": 0.0,
  "confidence_threshold": 0.6,
  "tags": [],
  "categories": [
    59
  ],
  "website": "https://highlightjs.org/"
}