{
  "$schema": "lia-fingerprint-v1",
  "id": "wappalyzer-php",
  "version": "1.0.0",
  "enabled": true,
  "taxonomy_code": "PHP",
  "taxonomy_name": "PHP",
  "vendor": "",
  "product": "PHP",
  "source": {
    "type": "wappalyzer",
    "file": "PHP.json",
    "original_name": "PHP"
  },
  "research": [
    {
      "url": "https://php.net",
      "type": "wappalyzer_database",
      "evidence": "Converted from wappalyzergo fingerprints_data.json",
      "date": "2026-02-28"
    }
  ],
  "default_ports": [
    80,
    443
  ],
  "probes": [
    {
      "id": "wappalyzer_php_http",
      "layer": "L7_HTTP",
      "method": "GET",
      "path": "/",
      "follow_redirects": true,
      "matchers": [
        {
          "target": "header",
          "field": "server",
          "confidence_delta": 0.5,
          "match_type": "regex",
          "value": "php/?([\\d.]+)?",
          "version_extract": "php/?([\\d.]+)?"
        },
        {
          "target": "header",
          "field": "x-powered-by",
          "confidence_delta": 0.5,
          "match_type": "regex",
          "value": "^php/?([\\d.]+)?",
          "version_extract": "^php/?([\\d.]+)?"
        },
        {
          "target": "cookie",
          "field": "phpsessid",
          "confidence_delta": 0.5,
          "match_type": "exists"
        }
      ]
    }
  ],
  "base_confidence": 0.0,
  "confidence_threshold": 0.6,
  "tags": [],
  "cpe23_template": "cpe:2.3:a:php:php:*:*:*:*:*:*:*:*",
  "categories": [
    27
  ],
  "notes": "PHP is a general-purpose scripting language used for web development.",
  "website": "https://php.net"
}