{
  "$schema": "lia-fingerprint-v1",
  "id": "wappalyzer-quintype",
  "version": "1.0.0",
  "enabled": true,
  "taxonomy_code": "QUINTYPE",
  "taxonomy_name": "Quintype",
  "vendor": "",
  "product": "Quintype",
  "source": {
    "type": "wappalyzer",
    "file": "QUINTYPE.json",
    "original_name": "Quintype"
  },
  "research": [
    {
      "url": "https://www.quintype.com",
      "type": "wappalyzer_database",
      "evidence": "Converted from wappalyzergo fingerprints_data.json",
      "date": "2026-02-28"
    }
  ],
  "default_ports": [
    80,
    443
  ],
  "probes": [
    {
      "id": "wappalyzer_quintype_http",
      "layer": "L7_HTTP",
      "method": "GET",
      "path": "/",
      "follow_redirects": true,
      "matchers": [
        {
          "target": "header",
          "field": "link",
          "confidence_delta": 0.5,
          "match_type": "regex",
          "value": "fea\\.assettype\\.com/quintype-ace"
        },
        {
          "target": "cookie",
          "field": "qtype-session",
          "confidence_delta": 0.5,
          "match_type": "exists"
        }
      ]
    }
  ],
  "base_confidence": 0.0,
  "confidence_threshold": 0.6,
  "tags": [],
  "categories": [
    1
  ],
  "notes": "Quintype is a digital publishing platform that provides content management, audience engagement, and monetisation solutions for digital media organisations.",
  "website": "https://www.quintype.com"
}