{
  "$schema": "lia-fingerprint-v1",
  "id": "wappalyzer-rankscience",
  "version": "1.0.0",
  "enabled": true,
  "taxonomy_code": "RANKSCIENCE",
  "taxonomy_name": "RankScience",
  "vendor": "",
  "product": "RankScience",
  "source": {
    "type": "wappalyzer",
    "file": "RANKSCIENCE.json",
    "original_name": "RankScience"
  },
  "research": [
    {
      "url": "https://www.rankscience.com",
      "type": "wappalyzer_database",
      "evidence": "Converted from wappalyzergo fingerprints_data.json",
      "date": "2026-02-28"
    }
  ],
  "default_ports": [
    80,
    443
  ],
  "probes": [
    {
      "id": "wappalyzer_rankscience_http",
      "layer": "L7_HTTP",
      "method": "GET",
      "path": "/",
      "follow_redirects": true,
      "matchers": [
        {
          "target": "script_src",
          "match_type": "regex",
          "value": "cdn\\.ranksci\\.com",
          "confidence_delta": 0.5
        }
      ]
    }
  ],
  "base_confidence": 0.0,
  "confidence_threshold": 0.6,
  "tags": [],
  "categories": [
    74
  ],
  "notes": "RankScience is a split testing platform that uses data science to optimize search traffic.",
  "website": "https://www.rankscience.com"
}