{
  "$schema": "lia-fingerprint-v1",
  "id": "wappalyzer-sellerscommerce",
  "version": "1.0.0",
  "enabled": true,
  "taxonomy_code": "SELLERSCOMMERCE",
  "taxonomy_name": "SellersCommerce",
  "vendor": "",
  "product": "SellersCommerce",
  "source": {
    "type": "wappalyzer",
    "file": "SELLERSCOMMERCE.json",
    "original_name": "SellersCommerce"
  },
  "research": [
    {
      "url": "https://www.sellerscommerce.com",
      "type": "wappalyzer_database",
      "evidence": "Converted from wappalyzergo fingerprints_data.json",
      "date": "2026-02-28"
    }
  ],
  "default_ports": [
    80,
    443
  ],
  "probes": [
    {
      "id": "wappalyzer_sellerscommerce_http",
      "layer": "L7_HTTP",
      "method": "GET",
      "path": "/",
      "follow_redirects": true,
      "matchers": [
        {
          "target": "script_src",
          "match_type": "regex",
          "value": "\\.sellerscommerce\\.com/",
          "confidence_delta": 0.5
        }
      ]
    }
  ],
  "base_confidence": 0.0,
  "confidence_threshold": 0.6,
  "tags": [],
  "categories": [
    6
  ],
  "notes": "SellersCommerce is a medium ecommerce software company that provides b2b ecommerce platform to retail companies.",
  "website": "https://www.sellerscommerce.com"
}