{
  "$schema": "lia-fingerprint-v1",
  "id": "wappalyzer-subversion",
  "version": "1.0.0",
  "enabled": true,
  "taxonomy_code": "SUBVERSION",
  "taxonomy_name": "Subversion",
  "vendor": "",
  "product": "Subversion",
  "source": {
    "type": "wappalyzer",
    "file": "SUBVERSION.json",
    "original_name": "Subversion"
  },
  "research": [
    {
      "url": "https://subversion.apache.org",
      "type": "wappalyzer_database",
      "evidence": "Converted from wappalyzergo fingerprints_data.json",
      "date": "2026-02-28"
    }
  ],
  "default_ports": [
    80,
    443
  ],
  "probes": [
    {
      "id": "wappalyzer_subversion_http",
      "layer": "L7_HTTP",
      "method": "GET",
      "path": "/",
      "follow_redirects": true,
      "matchers": [
        {
          "target": "header",
          "field": "server",
          "confidence_delta": 0.5,
          "match_type": "regex",
          "value": "\\ssvn/([\\d\\.]+)\\s",
          "version_extract": "\\ssvn/([\\d\\.]+)\\s"
        }
      ]
    }
  ],
  "base_confidence": 0.0,
  "confidence_threshold": 0.6,
  "tags": [],
  "cpe23_template": "cpe:2.3:a:apache:subversion:*:*:*:*:*:*:*:*",
  "categories": [
    47
  ],
  "notes": "Subversion is a centralized version control system for managing files and directories across software development teams.",
  "website": "https://subversion.apache.org"
}