{
  "$schema": "lia-fingerprint-v1",
  "id": "wappalyzer-voltage",
  "version": "1.0.0",
  "enabled": true,
  "taxonomy_code": "VOLTAGE",
  "taxonomy_name": "Voltage",
  "vendor": "",
  "product": "Voltage",
  "source": {
    "type": "wappalyzer",
    "file": "VOLTAGE.json",
    "original_name": "Voltage"
  },
  "research": [
    {
      "url": "https://www.voltage.cloud",
      "type": "wappalyzer_database",
      "evidence": "Converted from wappalyzergo fingerprints_data.json",
      "date": "2026-02-28"
    }
  ],
  "default_ports": [
    80,
    443
  ],
  "probes": [
    {
      "id": "wappalyzer_voltage_http",
      "layer": "L7_HTTP",
      "method": "GET",
      "path": "/",
      "follow_redirects": true,
      "matchers": [
        {
          "target": "script_src",
          "match_type": "regex",
          "value": "btcpay0\\.voltageapp\\.io",
          "confidence_delta": 0.5
        }
      ]
    }
  ],
  "base_confidence": 0.0,
  "confidence_threshold": 0.6,
  "tags": [],
  "categories": [
    41
  ],
  "notes": "Voltage is a payments platform that enables users to send bitcoin globally through a secure network.",
  "website": "https://www.voltage.cloud"
}